isubrip/__init__.py
isubrip/__main__.py
isubrip/cli.py
isubrip/config.py
isubrip/constants.py
isubrip/data_structures.py
isubrip/logger.py
isubrip/ui.py
isubrip/utils.py
isubrip/commands/__init__.py
isubrip/commands/download.py
isubrip/scrapers/__init__.py
isubrip/scrapers/appletv_scraper.py
isubrip/scrapers/itunes_scraper.py
isubrip/scrapers/scraper.py
isubrip/subtitle_formats/__init__.py
isubrip/subtitle_formats/subrip.py
isubrip/subtitle_formats/subtitles.py
isubrip/subtitle_formats/webvtt.py
isubrip-2.6.8.dist-info/METADATA
isubrip-2.6.8.dist-info/WHEEL
isubrip-2.6.8.dist-info/entry_points.txt
isubrip-2.6.8.dist-info/licenses/LICENSE
isubrip-2.6.8.dist-info/RECORD
