Metadata-Version: 2.4
Name: isubrip
Version: 2.6.8
Summary: A Python package for scraping and downloading subtitles from AppleTV / iTunes movie pages.
Project-URL: Homepage, https://github.com/MichaelYochpaz/iSubRip
Project-URL: Repository, https://github.com/MichaelYochpaz/iSubRip
Project-URL: Issues, https://github.com/MichaelYochpaz/iSubRip/issues
Project-URL: Changelog, https://github.com/MichaelYochpaz/iSubRip/blob/main/CHANGELOG.md
Author: Michael Yochpaz
License-File: LICENSE
Keywords: AppleTV,download,iTunes,m3u8,movies,scrape,scraper,subtitles
Classifier: Development Status :: 5 - Production/Stable
Classifier: Intended Audience :: End Users/Desktop
Classifier: License :: OSI Approved :: MIT License
Classifier: Operating System :: MacOS
Classifier: Operating System :: Microsoft :: Windows
Classifier: Operating System :: POSIX :: Linux
Classifier: Programming Language :: Python :: 3.10
Classifier: Programming Language :: Python :: 3.11
Classifier: Programming Language :: Python :: 3.12
Classifier: Programming Language :: Python :: 3.13
Classifier: Programming Language :: Python :: 3.14
Classifier: Topic :: Utilities
Requires-Python: >=3.10
Requires-Dist: httpx[http2]>=0.28.1
Requires-Dist: m3u8>=6.0.0
Requires-Dist: pydantic-settings>=2.11.0
Requires-Dist: pydantic>=2.12.0
Requires-Dist: pygments>=2.19.1
Requires-Dist: rich>=14.2.0
Requires-Dist: tomli>=2.3.0
Requires-Dist: wcwidth>=0.2.14
